{
  "title": "Keep It a Secret in School ",
  "description": "Donghwan is a well-known loser in school. He became more and more involved with the most popular girl in school, a queen bee, Soeun, until he found out about her secret...",
  "artist": "Seoul Forest Druid",
  "author": "Im Sua",
  "cover": "https://omegascans.org/_next/image?url=https%3A%2F%2Fmedia.omegascans.org%2Ffile%2FzFSsXt%2Fhqu5u9nguj5aqi7tvbskf9g0.jpg&w=640&q=75",
  "chapters": {
    "3": {
      "title": "3",
      "volume": "",
      "last_updated": "1732319688",
      "groups": {
        "": "/proxy/api/imgbox/chapter/lfVNPDir0k"
      }
    },
    "4": {
      "title": "4",
      "volume": "",
      "last_updated": "1732319852",
      "groups": {
        "": "/proxy/api/imgbox/chapter/e9IpdsCgAD"
      }
    },
    "5": {
      "title": "5",
      "volume": "",
      "last_updated": "1732318098",
      "groups": {
        "": "/proxy/api/imgbox/chapter/7wpC6ErtQ5"
      }
    },
    "6": {
      "title": "6",
      "volume": "",
      "last_updated": "1732320363",
      "groups": {
        "": "/proxy/api/imgbox/chapter/v8l1mMFuNK"
      }
    },
    "7": {
      "title": "7",
      "volume": "",
      "last_updated": "1732322045",
      "groups": {
        "Omega Scans": "/proxy/api/imgbox/chapter/eVDcFbhRJl"
      }
    },
    "8": {
      "title": "8",
      "volume": "",
      "last_updated": "1732322592",
      "groups": {
        "Omega Scans": "/proxy/api/imgbox/chapter/B5lJPwVvbX"
      }
    },
    "9": {
      "title": "9",
      "volume": "",
      "last_updated": "1733190370",
      "groups": {
        "Omega Scans": "/proxy/api/imgur/chapter/vegoot8"
      }
    },
    "10": {
      "title": "10",
      "volume": "",
      "last_updated": "1734965674",
      "groups": {
        "Omega Scans": "/proxy/api/imgbox/chapter/31mYOaSeZT"
      }
    },
    "11": {
      "title": "11",
      "volume": "",
      "last_updated": "1734965811",
      "groups": {
        "Omega Scans": "/proxy/api/imgbox/chapter/8WiNGH6Y0i"
      }
    },
    "12": {
      "title": "12",
      "volume": "",
      "last_updated": "1735372286",
      "groups": {
        "Omega Scans": "/proxy/api/imgbox/chapter/5TS0DRQgha"
      }
    },
    "13": {
      "title": "13",
      "volume": "",
      "last_updated": "1736717224",
      "groups": {
        "Omega Scans": "/proxy/api/imgbox/chapter/K8QZSlQ0NC"
      }
    },
    "14": {
      "title": "14",
      "volume": "",
      "last_updated": "1736722415",
      "groups": {
        "Omega Scans": "/proxy/api/imgbox/chapter/5xMJ0Qjs5p"
      }
    },
    "15": {
      "title": "15",
      "volume": "",
      "last_updated": "1736962437",
      "groups": {
        "Omega Scans": "/proxy/api/imgbox/chapter/Z6YrgUPqI1"
      }
    },
    "16": {
      "title": "16",
      "volume": "",
      "last_updated": "1738266240",
      "groups": {
        "Omega Scans": "/proxy/api/imgur/chapter/VfnglwP"
      }
    }
  }
}