{
  "title": "Park Moojik Hit the Jackpot",
  "description": "Park Moojik, an employee of a game company, picked up a bug item while playing the game. Since then, strange things started happening.",
  "artist": "",
  "author": "Coco Doer",
  "cover": "https://omegascans.org/_next/image?url=https%3A%2F%2Fmedia.omegascans.org%2Ffile%2FzFSsXt%2Fcovers%2F8cf84882-439d-4995-83c1-df3c5361e95e.jpg&w=640&q=75",
  "chapters": {
    "22": {
      "title": "22",
      "volume": "",
      "last_updated": "1717633306",
      "groups": {
        "": "/proxy/api/imgbox/chapter/04nkCuG8KB"
      }
    },
    "23": {
      "title": "23",
      "volume": "",
      "last_updated": "1718065001",
      "groups": {
        "": "/proxy/api/imgbox/chapter/0eRfTRMGqq"
      }
    },
    "24": {
      "title": "24",
      "volume": "",
      "last_updated": "1718737440",
      "groups": {
        "": "/proxy/api/imgbox/chapter/c3KKOWfXp5"
      }
    }
  }
}