{
  "title": "Yogurt Delivery Lady",
  "description": "Rumor has it, there's a yogurt lady who eats men's yogurt in a one-bedroom village at a university. To verify the rumor, Junwoo asks Sohee, the yogurt lady he secretly likes. \"Ahjumma, I wanna eat Junwoo's yogurt.\"",
  "artist": "",
  "author": "SaraJin, - & ttwook",
  "cover": "https://omegascans.org/_next/image?url=https%3A%2F%2Fmedia.omegascans.org%2Ffile%2FzFSsXt%2Flpnga4z8ib47ln7mqnabn9ls.webp&w=640&q=75",
  "chapters": {
    "2": {
      "title": "2",
      "volume": "1",
      "last_updated": "1713444318",
      "groups": {
        "Omega Scans": "/proxy/api/imgbox/chapter/UdDxLKzr8t"
      }
    },
    "3": {
      "title": "3",
      "volume": "1",
      "last_updated": "1713446133",
      "groups": {
        "Omega Scans": "/proxy/api/imgbox/chapter/RoqSKhURLW"
      }
    },
    "31": {
      "title": "31",
      "volume": "1",
      "last_updated": "1730126598",
      "groups": {
        "Omega Scans": "/proxy/api/imgbox/chapter/QAJFxLJ7S2"
      }
    },
    "32": {
      "title": "32",
      "volume": "1",
      "last_updated": "1730182978",
      "groups": {
        "Omega Scans": "/proxy/api/imgbox/chapter/3Ns51mDqAs"
      }
    },
    "33": {
      "title": "33",
      "volume": "1",
      "last_updated": "1731580504",
      "groups": {
        "Omega Scans": "/proxy/api/imgbox/chapter/fHbChDr2fe"
      }
    },
    "34": {
      "title": "34",
      "volume": "1",
      "last_updated": "1731723009",
      "groups": {
        "Omega Scans": "/proxy/api/imgbox/chapter/FAHFR1OC4A"
      }
    },
    "35": {
      "title": "35",
      "volume": "1",
      "last_updated": "1732932907",
      "groups": {
        "Omega Scans": "/proxy/api/imgbox/chapter/2nLkLomz6q"
      }
    },
    "36": {
      "title": "36",
      "volume": "1",
      "last_updated": "1732932966",
      "groups": {
        "Omega Scans": "/proxy/api/imgbox/chapter/4eTWuSCs7b"
      }
    },
    "37": {
      "title": "37",
      "volume": "1",
      "last_updated": "1734270453",
      "groups": {
        "Omega Scans": "/proxy/api/imgbox/chapter/jO3sD2lnwC"
      }
    },
    "38": {
      "title": "38",
      "volume": "1",
      "last_updated": "1734880389",
      "groups": {
        "Omega Scans": "/proxy/api/imgbox/chapter/ED5y6UFKXk"
      }
    },
    "39": {
      "title": "39",
      "volume": "1",
      "last_updated": "1734880444",
      "groups": {
        "Omega Scans": "/proxy/api/imgbox/chapter/v2OzdF8TNE"
      }
    },
    "40": {
      "title": "40",
      "volume": "1",
      "last_updated": "1735793118",
      "groups": {
        "Omega Scans": "/proxy/api/imgbox/chapter/S5SU6NSUOP"
      }
    },
    "41": {
      "title": "41",
      "volume": "1",
      "last_updated": "1736052190",
      "groups": {
        "Omega Scans": "/proxy/api/imgbox/chapter/VeViM9FsHQ"
      }
    },
    "42": {
      "title": "42",
      "volume": "1",
      "last_updated": "1737028857",
      "groups": {
        "Omega Scans": "/proxy/api/imgbox/chapter/FZMJLsrz6d"
      }
    },
    "43": {
      "title": "43",
      "volume": "1",
      "last_updated": "1737552491",
      "groups": {
        "Omega Scans": "/proxy/api/imgbox/chapter/dz4BK3qsSk"
      }
    },
    "44": {
      "title": "44",
      "volume": "1",
      "last_updated": "1737850537",
      "groups": {
        "Omega Scans": "/proxy/api/imgbox/chapter/bkb0aIpDCY"
      }
    },
    "45": {
      "title": "45",
      "volume": "1",
      "last_updated": "1738890465",
      "groups": {
        "Omega Scans": "/proxy/api/imgbox/chapter/EX6IBfnSS9"
      }
    },
    "46": {
      "title": "46",
      "volume": "1",
      "last_updated": "1738986811",
      "groups": {
        "Omega Scans": "/proxy/api/imgbox/chapter/aOomT1tEtg"
      }
    },
    "47": {
      "title": "47",
      "volume": "1",
      "last_updated": "1739933496",
      "groups": {
        "Omega Scans": "/proxy/api/imgbox/chapter/k0m8bw0HWH"
      }
    }
  }
}